addok_sqlite_store/__init__.py
addok_sqlite_store-1.0.1.dist-info/LICENSE
addok_sqlite_store-1.0.1.dist-info/METADATA
addok_sqlite_store-1.0.1.dist-info/WHEEL
addok_sqlite_store-1.0.1.dist-info/entry_points.txt
addok_sqlite_store-1.0.1.dist-info/top_level.txt
addok_sqlite_store-1.0.1.dist-info/RECORD
