Metadata-Version: 2.1
Name: addok-sqlite-store
Version: 1.0.1
Summary: Store documents in Sqlite.
Home-page: https://github.com/addok/addok-sqlite-store
Author: Yohan Boniface
Author-email: yohan.boniface@data.gouv.fr
License: WTFPL
Keywords: addok geocoding sqlite plugin
Classifier: Development Status :: 4 - Beta
Classifier: Intended Audience :: Developers
Classifier: Topic :: Scientific/Engineering :: GIS
Classifier: Programming Language :: Python :: 3
Classifier: Programming Language :: Python :: 3.4
Classifier: Programming Language :: Python :: 3.5
Classifier: Programming Language :: Python :: 3.6
License-File: LICENSE
Provides-Extra: test
Requires-Dist: pytest ; extra == 'test'
